[
  {
    "Domain Code": "QCL",
    "Domain": "Crops and livestock products",
    "Area Code": 2,
    "Area": "Afghanistan",
    "Element Code": 5510,
    "Element": "Production",
    "Item Code": 27,
    "Item": "Rice",
    "Unit": "t",
    "Value": 444781.31,
    "Flag": "E",
    "Flag Description": "Estimated value"
  },
  {
    "Domain Code": "QCL",
    "Domain": "Crops and livestock products",
    "Area Code": 3,
    "Area": "Albania",
    "Element Code": 5510,
    "Element": "Production",
    "Item Code": 27,
    "Item": "Rice",
    "Unit": "t",
    "Value": 0,
    "Flag": "E",
    "Flag Description": "Estimated value"
  },
  {
    "Domain Code": "QCL",
    "Domain": "Crops and livestock products",
    "Area Code": 4,
    "Area": "Algeria",
    "Element Code": 5510,
    "Element": "Production",
    "Item Code": 27,
    "Item": "Rice",
    "Unit": "t",
    "Value": 439.45,
    "Flag": "E",
    "Flag Description": "Estimated value"
  },
  {
    "Domain Code": "QCL",
    "Domain": "Crops and livestock products",
    "Area Code": 7,
    "Area": "Angola",
    "Element Code": 5510,
    "Element": "Production",
    "Item Code": 27,
    "Item": "Rice",
    "Unit": "t",
    "Value": 15198.39,
    "Flag": "E",
    "Flag Description": "Estimated value"
  },
  {
    "Domain Code": "QCL",
    "Domain": "Crops and livestock products",
    "Area Code": 9,
    "Area": "Argentina",
    "Element Code": 5510,
    "Element": "Production",
    "Item Code": 27,
    "Item": "Rice",
    "Unit": "t",
    "Value": 1203492.21,
    "Flag": "E",
    "Flag Description": "Estimated value"
  },
  {
    "Domain Code": "QCL",
    "Domain": "Crops and livestock products",
    "Area Code": 1,
    "Area": "Armenia",
    "Element Code": 5510,
    "Element": "Production",
    "Item Code": 27,
    "Item": "Rice",
    "Unit": "t",
    "Value": 0,
    "Flag": "E",
    "Flag Description": "Estimated value"
  },
  {
    "Domain Code": "QCL",
    "Domain": "Crops and livestock products",
    "Area Code": 10,
    "Area": "Australia",
    "Element Code": 5510,
    "Element": "Production",
    "Item Code": 27,
    "Item": "Rice",
    "Unit": "t",
    "Value": 734112.02,
    "Flag": "E",
    "Flag Description": "Estimated value"
  },
  {
    "Domain Code": "QCL",
    "Domain": "Crops and livestock products",
    "Area Code": 52,
    "Area": "Azerbaijan",
    "Element Code": 5510,
    "Element": "Production",
    "Item Code": 27,
    "Item": "Rice",
    "Unit": "t",
    "Value": 8750.92,
    "Flag": "E",
    "Flag Description": "Estimated value"
  },
  {
    "Domain Code": "QCL",
    "Domain": "Crops and livestock products",
    "Area Code": 16,
    "Area": "Bangladesh",
    "Element Code": 5510,
    "Element": "Production",
    "Item Code": 27,
    "Item": "Rice",
    "Unit": "t",
    "Value": 43160872.28,
    "Flag": "E",
    "Flag Description": "Estimated value"
  },
  {
    "Domain Code": "QCL",
    "Domain": "Crops and livestock products",
    "Area Code": 255,
    "Area": "Belgium",
    "Element Code": 5510,
    "Element": "Production",
    "Item Code": 27,
    "Item": "Rice",
    "Unit": "t",
    "Value": 0,
    "Flag": "E",
    "Flag Description": "Estimated value"
  },
  {
    "Domain Code": "QCL",
    "Domain": "Crops and livestock products",
    "Area Code": 23,
    "Area": "Belize",
    "Element Code": 5510,
    "Element": "Production",
    "Item Code": 27,
    "Item": "Rice",
    "Unit": "t",
    "Value": 14140.96,
    "Flag": "E",
    "Flag Description": "Estimated value"
  },
  {
    "Domain Code": "QCL",
    "Domain": "Crops and livestock products",
    "Area Code": 53,
    "Area": "Benin",
    "Element Code": 5510,
    "Element": "Production",
    "Item Code": 27,
    "Item": "Rice",
    "Unit": "t",
    "Value": 165287.87,
    "Flag": "E",
    "Flag Description": "Estimated value"
  },
  {
    "Domain Code": "QCL",
    "Domain": "Crops and livestock products",
    "Area Code": 18,
    "Area": "Bhutan",
    "Element Code": 5510,
    "Element": "Production",
    "Item Code": 27,
    "Item": "Rice",
    "Unit": "t",
    "Value": 61087.93,
    "Flag": "E",
    "Flag Description": "Estimated value"
  },
  {
    "Domain Code": "QCL",
    "Domain": "Crops and livestock products",
    "Area Code": 19,
    "Area": "Bolivia (Plurinational State of)",
    "Element Code": 5510,
    "Element": "Production",
    "Item Code": 27,
    "Item": "Rice",
    "Unit": "t",
    "Value": 399986.6,
    "Flag": "E",
    "Flag Description": "Estimated value"
  },
  {
    "Domain Code": "QCL",
    "Domain": "Crops and livestock products",
    "Area Code": 21,
    "Area": "Brazil",
    "Element Code": 5510,
    "Element": "Production",
    "Item Code": 27,
    "Item": "Rice",
    "Unit": "t",
    "Value": 11235847.54,
    "Flag": "E",
    "Flag Description": "Estimated value"
  },
  {
    "Domain Code": "QCL",
    "Domain": "Crops and livestock products",
    "Area Code": 26,
    "Area": "Brunei Darussalam",
    "Element Code": 5510,
    "Element": "Production",
    "Item Code": 27,
    "Item": "Rice",
    "Unit": "t",
    "Value": 1064.72,
    "Flag": "E",
    "Flag Description": "Estimated value"
  },
  {
    "Domain Code": "QCL",
    "Domain": "Crops and livestock products",
    "Area Code": 27,
    "Area": "Bulgaria",
    "Element Code": 5510,
    "Element": "Production",
    "Item Code": 27,
    "Item": "Rice",
    "Unit": "t",
    "Value": 36868.86,
    "Flag": "E",
    "Flag Description": "Estimated value"
  },
  {
    "Domain Code": "QCL",
    "Domain": "Crops and livestock products",
    "Area Code": 233,
    "Area": "Burkina Faso",
    "Element Code": 5510,
    "Element": "Production",
    "Item Code": 27,
    "Item": "Rice",
    "Unit": "t",
    "Value": 208391.69,
    "Flag": "E",
    "Flag Description": "Estimated value"
  },
  {
    "Domain Code": "QCL",
    "Domain": "Crops and livestock products",
    "Area Code": 29,
    "Area": "Burundi",
    "Element Code": 5510,
    "Element": "Production",
    "Item Code": 27,
    "Item": "Rice",
    "Unit": "t",
    "Value": 76823.81,
    "Flag": "E",
    "Flag Description": "Estimated value"
  },
  {
    "Domain Code": "QCL",
    "Domain": "Crops and livestock products",
    "Area Code": 115,
    "Area": "Cambodia",
    "Element Code": 5510,
    "Element": "Production",
    "Item Code": 27,
    "Item": "Rice",
    "Unit": "t",
    "Value": 6924231.14,
    "Flag": "E",
    "Flag Description": "Estimated value"
  },
  {
    "Domain Code": "QCL",
    "Domain": "Crops and livestock products",
    "Area Code": 32,
    "Area": "Cameroon",
    "Element Code": 5510,
    "Element": "Production",
    "Item Code": 27,
    "Item": "Rice",
    "Unit": "t",
    "Value": 144746.42,
    "Flag": "E",
    "Flag Description": "Estimated value"
  },
  {
    "Domain Code": "QCL",
    "Domain": "Crops and livestock products",
    "Area Code": 37,
    "Area": "Central African Republic",
    "Element Code": 5510,
    "Element": "Production",
    "Item Code": 27,
    "Item": "Rice",
    "Unit": "t",
    "Value": 23422.71,
    "Flag": "E",
    "Flag Description": "Estimated value"
  },
  {
    "Domain Code": "QCL",
    "Domain": "Crops and livestock products",
    "Area Code": 39,
    "Area": "Chad",
    "Element Code": 5510,
    "Element": "Production",
    "Item Code": 27,
    "Item": "Rice",
    "Unit": "t",
    "Value": 176062.26,
    "Flag": "E",
    "Flag Description": "Estimated value"
  },
  {
    "Domain Code": "QCL",
    "Domain": "Crops and livestock products",
    "Area Code": 40,
    "Area": "Chile",
    "Element Code": 5510,
    "Element": "Production",
    "Item Code": 27,
    "Item": "Rice",
    "Unit": "t",
    "Value": 135362.01,
    "Flag": "E",
    "Flag Description": "Estimated value"
  },
  {
    "Domain Code": "QCL",
    "Domain": "Crops and livestock products",
    "Area Code": 351,
    "Area": "China",
    "Element Code": 5510,
    "Element": "Production",
    "Item Code": 27,
    "Item": "Rice",
    "Unit": "t",
    "Value": 196811191.5,
    "Flag": "E",
    "Flag Description": "Estimated value"
  },
  {
    "Domain Code": "QCL",
    "Domain": "Crops and livestock products",
    "Area Code": 96,
    "Area": "China, Hong Kong SAR",
    "Element Code": 5510,
    "Element": "Production",
    "Item Code": 27,
    "Item": "Rice",
    "Unit": "t",
    "Value": 0.04,
    "Flag": "E",
    "Flag Description": "Estimated value"
  },
  {
    "Domain Code": "QCL",
    "Domain": "Crops and livestock products",
    "Area Code": 41,
    "Area": "China, mainland",
    "Element Code": 5510,
    "Element": "Production",
    "Item Code": 27,
    "Item": "Rice",
    "Unit": "t",
    "Value": 195099192.14,
    "Flag": "E",
    "Flag Description": "Estimated value"
  },
  {
    "Domain Code": "QCL",
    "Domain": "Crops and livestock products",
    "Area Code": 214,
    "Area": "China, Taiwan Province of",
    "Element Code": 5510,
    "Element": "Production",
    "Item Code": 27,
    "Item": "Rice",
    "Unit": "t",
    "Value": 1711999.32,
    "Flag": "E",
    "Flag Description": "Estimated value"
  },
  {
    "Domain Code": "QCL",
    "Domain": "Crops and livestock products",
    "Area Code": 44,
    "Area": "Colombia",
    "Element Code": 5510,
    "Element": "Production",
    "Item Code": 27,
    "Item": "Rice",
    "Unit": "t",
    "Value": 2342650.49,
    "Flag": "E",
    "Flag Description": "Estimated value"
  },
  {
    "Domain Code": "QCL",
    "Domain": "Crops and livestock products",
    "Area Code": 45,
    "Area": "Comoros",
    "Element Code": 5510,
    "Element": "Production",
    "Item Code": 27,
    "Item": "Rice",
    "Unit": "t",
    "Value": 22833.47,
    "Flag": "E",
    "Flag Description": "Estimated value"
  },
  {
    "Domain Code": "QCL",
    "Domain": "Crops and livestock products",
    "Area Code": 46,
    "Area": "Congo",
    "Element Code": 5510,
    "Element": "Production",
    "Item Code": 27,
    "Item": "Rice",
    "Unit": "t",
    "Value": 1214.62,
    "Flag": "E",
    "Flag Description": "Estimated value"
  },
  {
    "Domain Code": "QCL",
    "Domain": "Crops and livestock products",
    "Area Code": 48,
    "Area": "Costa Rica",
    "Element Code": 5510,
    "Element": "Production",
    "Item Code": 27,
    "Item": "Rice",
    "Unit": "t",
    "Value": 209506.19,
    "Flag": "E",
    "Flag Description": "Estimated value"
  },
  {
    "Domain Code": "QCL",
    "Domain": "Crops and livestock products",
    "Area Code": 107,
    "Area": "Côte d'Ivoire",
    "Element Code": 5510,
    "Element": "Production",
    "Item Code": 27,
    "Item": "Rice",
    "Unit": "t",
    "Value": 1124768.39,
    "Flag": "E",
    "Flag Description": "Estimated value"
  },
  {
    "Domain Code": "QCL",
    "Domain": "Crops and livestock products",
    "Area Code": 98,
    "Area": "Croatia",
    "Element Code": 5510,
    "Element": "Production",
    "Item Code": 27,
    "Item": "Rice",
    "Unit": "t",
    "Value": 0,
    "Flag": "E",
    "Flag Description": "Estimated value"
  },
  {
    "Domain Code": "QCL",
    "Domain": "Crops and livestock products",
    "Area Code": 49,
    "Area": "Cuba",
    "Element Code": 5510,
    "Element": "Production",
    "Item Code": 27,
    "Item": "Rice",
    "Unit": "t",
    "Value": 495164.57,
    "Flag": "E",
    "Flag Description": "Estimated value"
  },
  {
    "Domain Code": "QCL",
    "Domain": "Crops and livestock products",
    "Area Code": 50,
    "Area": "Cyprus",
    "Element Code": 5510,
    "Element": "Production",
    "Item Code": 27,
    "Item": "Rice",
    "Unit": "t",
    "Value": 0,
    "Flag": "E",
    "Flag Description": "Estimated value"
  },
  {
    "Domain Code": "QCL",
    "Domain": "Crops and livestock products",
    "Area Code": 167,
    "Area": "Czechia",
    "Element Code": 5510,
    "Element": "Production",
    "Item Code": 27,
    "Item": "Rice",
    "Unit": "t",
    "Value": 0,
    "Flag": "E",
    "Flag Description": "Estimated value"
  },
  {
    "Domain Code": "QCL",
    "Domain": "Crops and livestock products",
    "Area Code": 116,
    "Area": "Democratic People's Republic of Korea",
    "Element Code": 5510,
    "Element": "Production",
    "Item Code": 27,
    "Item": "Rice",
    "Unit": "t",
    "Value": 2303339,
    "Flag": "E",
    "Flag Description": "Estimated value"
  },
  {
    "Domain Code": "QCL",
    "Domain": "Crops and livestock products",
    "Area Code": 250,
    "Area": "Democratic Republic of the Congo",
    "Element Code": 5510,
    "Element": "Production",
    "Item Code": 27,
    "Item": "Rice",
    "Unit": "t",
    "Value": 655915.99,
    "Flag": "E",
    "Flag Description": "Estimated value"
  },
  {
    "Domain Code": "QCL",
    "Domain": "Crops and livestock products",
    "Area Code": 54,
    "Area": "Denmark",
    "Element Code": 5510,
    "Element": "Production",
    "Item Code": 27,
    "Item": "Rice",
    "Unit": "t",
    "Value": 0,
    "Flag": "E",
    "Flag Description": "Estimated value"
  },
  {
    "Domain Code": "QCL",
    "Domain": "Crops and livestock products",
    "Area Code": 56,
    "Area": "Dominican Republic",
    "Element Code": 5510,
    "Element": "Production",
    "Item Code": 27,
    "Item": "Rice",
    "Unit": "t",
    "Value": 724168.08,
    "Flag": "E",
    "Flag Description": "Estimated value"
  },
  {
    "Domain Code": "QCL",
    "Domain": "Crops and livestock products",
    "Area Code": 58,
    "Area": "Ecuador",
    "Element Code": 5510,
    "Element": "Production",
    "Item Code": 27,
    "Item": "Rice",
    "Unit": "t",
    "Value": 1426082.87,
    "Flag": "E",
    "Flag Description": "Estimated value"
  },
  {
    "Domain Code": "QCL",
    "Domain": "Crops and livestock products",
    "Area Code": 59,
    "Area": "Egypt",
    "Element Code": 5510,
    "Element": "Production",
    "Item Code": 27,
    "Item": "Rice",
    "Unit": "t",
    "Value": 5435635.22,
    "Flag": "E",
    "Flag Description": "Estimated value"
  },
  {
    "Domain Code": "QCL",
    "Domain": "Crops and livestock products",
    "Area Code": 60,
    "Area": "El Salvador",
    "Element Code": 5510,
    "Element": "Production",
    "Item Code": 27,
    "Item": "Rice",
    "Unit": "t",
    "Value": 36899.79,
    "Flag": "E",
    "Flag Description": "Estimated value"
  },
  {
    "Domain Code": "QCL",
    "Domain": "Crops and livestock products",
    "Area Code": 63,
    "Area": "Estonia",
    "Element Code": 5510,
    "Element": "Production",
    "Item Code": 27,
    "Item": "Rice",
    "Unit": "t",
    "Value": 0,
    "Flag": "E",
    "Flag Description": "Estimated value"
  },
  {
    "Domain Code": "QCL",
    "Domain": "Crops and livestock products",
    "Area Code": 209,
    "Area": "Eswatini",
    "Element Code": 5510,
    "Element": "Production",
    "Item Code": 27,
    "Item": "Rice",
    "Unit": "t",
    "Value": 631.22,
    "Flag": "E",
    "Flag Description": "Estimated value"
  },
  {
    "Domain Code": "QCL",
    "Domain": "Crops and livestock products",
    "Area Code": 238,
    "Area": "Ethiopia",
    "Element Code": 5510,
    "Element": "Production",
    "Item Code": 27,
    "Item": "Rice",
    "Unit": "t",
    "Value": 69652.5,
    "Flag": "E",
    "Flag Description": "Estimated value"
  },
  {
    "Domain Code": "QCL",
    "Domain": "Crops and livestock products",
    "Area Code": 66,
    "Area": "Fiji",
    "Element Code": 5510,
    "Element": "Production",
    "Item Code": 27,
    "Item": "Rice",
    "Unit": "t",
    "Value": 11465.83,
    "Flag": "E",
    "Flag Description": "Estimated value"
  },
  {
    "Domain Code": "QCL",
    "Domain": "Crops and livestock products",
    "Area Code": 67,
    "Area": "Finland",
    "Element Code": 5510,
    "Element": "Production",
    "Item Code": 27,
    "Item": "Rice",
    "Unit": "t",
    "Value": 0,
    "Flag": "E",
    "Flag Description": "Estimated value"
  },
  {
    "Domain Code": "QCL",
    "Domain": "Crops and livestock products",
    "Area Code": 68,
    "Area": "France",
    "Element Code": 5510,
    "Element": "Production",
    "Item Code": 27,
    "Item": "Rice",
    "Unit": "t",
    "Value": 103623.56,
    "Flag": "E",
    "Flag Description": "Estimated value"
  },
  {
    "Domain Code": "QCL",
    "Domain": "Crops and livestock products",
    "Area Code": 69,
    "Area": "French Guiana",
    "Element Code": 5510,
    "Element": "Production",
    "Item Code": 27,
    "Item": "Rice",
    "Unit": "t",
    "Value": 24066.54,
    "Flag": "E",
    "Flag Description": "Estimated value"
  },
  {
    "Domain Code": "QCL",
    "Domain": "Crops and livestock products",
    "Area Code": 74,
    "Area": "Gabon",
    "Element Code": 5510,
    "Element": "Production",
    "Item Code": 27,
    "Item": "Rice",
    "Unit": "t",
    "Value": 1302.34,
    "Flag": "E",
    "Flag Description": "Estimated value"
  },
  {
    "Domain Code": "QCL",
    "Domain": "Crops and livestock products",
    "Area Code": 75,
    "Area": "Gambia",
    "Element Code": 5510,
    "Element": "Production",
    "Item Code": 27,
    "Item": "Rice",
    "Unit": "t",
    "Value": 37554.71,
    "Flag": "E",
    "Flag Description": "Estimated value"
  },
  {
    "Domain Code": "QCL",
    "Domain": "Crops and livestock products",
    "Area Code": 79,
    "Area": "Germany",
    "Element Code": 5510,
    "Element": "Production",
    "Item Code": 27,
    "Item": "Rice",
    "Unit": "t",
    "Value": 0,
    "Flag": "E",
    "Flag Description": "Estimated value"
  },
  {
    "Domain Code": "QCL",
    "Domain": "Crops and livestock products",
    "Area Code": 81,
    "Area": "Ghana",
    "Element Code": 5510,
    "Element": "Production",
    "Item Code": 27,
    "Item": "Rice",
    "Unit": "t",
    "Value": 444778.23,
    "Flag": "E",
    "Flag Description": "Estimated value"
  },
  {
    "Domain Code": "QCL",
    "Domain": "Crops and livestock products",
    "Area Code": 84,
    "Area": "Greece",
    "Element Code": 5510,
    "Element": "Production",
    "Item Code": 27,
    "Item": "Rice",
    "Unit": "t",
    "Value": 209020.77,
    "Flag": "E",
    "Flag Description": "Estimated value"
  },
  {
    "Domain Code": "QCL",
    "Domain": "Crops and livestock products",
    "Area Code": 89,
    "Area": "Guatemala",
    "Element Code": 5510,
    "Element": "Production",
    "Item Code": 27,
    "Item": "Rice",
    "Unit": "t",
    "Value": 29142.48,
    "Flag": "E",
    "Flag Description": "Estimated value"
  },
  {
    "Domain Code": "QCL",
    "Domain": "Crops and livestock products",
    "Area Code": 90,
    "Area": "Guinea",
    "Element Code": 5510,
    "Element": "Production",
    "Item Code": 27,
    "Item": "Rice",
    "Unit": "t",
    "Value": 1568272.39,
    "Flag": "E",
    "Flag Description": "Estimated value"
  },
  {
    "Domain Code": "QCL",
    "Domain": "Crops and livestock products",
    "Area Code": 175,
    "Area": "Guinea-Bissau",
    "Element Code": 5510,
    "Element": "Production",
    "Item Code": 27,
    "Item": "Rice",
    "Unit": "t",
    "Value": 142588.54,
    "Flag": "E",
    "Flag Description": "Estimated value"
  },
  {
    "Domain Code": "QCL",
    "Domain": "Crops and livestock products",
    "Area Code": 91,
    "Area": "Guyana",
    "Element Code": 5510,
    "Element": "Production",
    "Item Code": 27,
    "Item": "Rice",
    "Unit": "t",
    "Value": 558569.3,
    "Flag": "E",
    "Flag Description": "Estimated value"
  },
  {
    "Domain Code": "QCL",
    "Domain": "Crops and livestock products",
    "Area Code": 93,
    "Area": "Haiti",
    "Element Code": 5510,
    "Element": "Production",
    "Item Code": 27,
    "Item": "Rice",
    "Unit": "t",
    "Value": 134125.47,
    "Flag": "E",
    "Flag Description": "Estimated value"
  },
  {
    "Domain Code": "QCL",
    "Domain": "Crops and livestock products",
    "Area Code": 95,
    "Area": "Honduras",
    "Element Code": 5510,
    "Element": "Production",
    "Item Code": 27,
    "Item": "Rice",
    "Unit": "t",
    "Value": 41465.19,
    "Flag": "E",
    "Flag Description": "Estimated value"
  },
  {
    "Domain Code": "QCL",
    "Domain": "Crops and livestock products",
    "Area Code": 97,
    "Area": "Hungary",
    "Element Code": 5510,
    "Element": "Production",
    "Item Code": 27,
    "Item": "Rice",
    "Unit": "t",
    "Value": 9898.89,
    "Flag": "E",
    "Flag Description": "Estimated value"
  },
  {
    "Domain Code": "QCL",
    "Domain": "Crops and livestock products",
    "Area Code": 100,
    "Area": "India",
    "Element Code": 5510,
    "Element": "Production",
    "Item Code": 27,
    "Item": "Rice",
    "Unit": "t",
    "Value": 145925175.75,
    "Flag": "E",
    "Flag Description": "Estimated value"
  },
  {
    "Domain Code": "QCL",
    "Domain": "Crops and livestock products",
    "Area Code": 101,
    "Area": "Indonesia",
    "Element Code": 5510,
    "Element": "Production",
    "Item Code": 27,
    "Item": "Rice",
    "Unit": "t",
    "Value": 54517783.83,
    "Flag": "E",
    "Flag Description": "Estimated value"
  },
  {
    "Domain Code": "QCL",
    "Domain": "Crops and livestock products",
    "Area Code": 102,
    "Area": "Iran (Islamic Republic of)",
    "Element Code": 5510,
    "Element": "Production",
    "Item Code": 27,
    "Item": "Rice",
    "Unit": "t",
    "Value": 2358276.58,
    "Flag": "E",
    "Flag Description": "Estimated value"
  },
  {
    "Domain Code": "QCL",
    "Domain": "Crops and livestock products",
    "Area Code": 103,
    "Area": "Iraq",
    "Element Code": 5510,
    "Element": "Production",
    "Item Code": 27,
    "Item": "Rice",
    "Unit": "t",
    "Value": 271403.5,
    "Flag": "E",
    "Flag Description": "Estimated value"
  },
  {
    "Domain Code": "QCL",
    "Domain": "Crops and livestock products",
    "Area Code": 104,
    "Area": "Ireland",
    "Element Code": 5510,
    "Element": "Production",
    "Item Code": 27,
    "Item": "Rice",
    "Unit": "t",
    "Value": 0,
    "Flag": "E",
    "Flag Description": "Estimated value"
  },
  {
    "Domain Code": "QCL",
    "Domain": "Crops and livestock products",
    "Area Code": 106,
    "Area": "Italy",
    "Element Code": 5510,
    "Element": "Production",
    "Item Code": 27,
    "Item": "Rice",
    "Unit": "t",
    "Value": 1450351.5,
    "Flag": "E",
    "Flag Description": "Estimated value"
  },
  {
    "Domain Code": "QCL",
    "Domain": "Crops and livestock products",
    "Area Code": 109,
    "Area": "Jamaica",
    "Element Code": 5510,
    "Element": "Production",
    "Item Code": 27,
    "Item": "Rice",
    "Unit": "t",
    "Value": 65.26,
    "Flag": "E",
    "Flag Description": "Estimated value"
  },
  {
    "Domain Code": "QCL",
    "Domain": "Crops and livestock products",
    "Area Code": 110,
    "Area": "Japan",
    "Element Code": 5510,
    "Element": "Production",
    "Item Code": 27,
    "Item": "Rice",
    "Unit": "t",
    "Value": 11277537.5,
    "Flag": "E",
    "Flag Description": "Estimated value"
  },
  {
    "Domain Code": "QCL",
    "Domain": "Crops and livestock products",
    "Area Code": 108,
    "Area": "Kazakhstan",
    "Element Code": 5510,
    "Element": "Production",
    "Item Code": 27,
    "Item": "Rice",
    "Unit": "t",
    "Value": 329672.91,
    "Flag": "E",
    "Flag Description": "Estimated value"
  },
  {
    "Domain Code": "QCL",
    "Domain": "Crops and livestock products",
    "Area Code": 114,
    "Area": "Kenya",
    "Element Code": 5510,
    "Element": "Production",
    "Item Code": 27,
    "Item": "Rice",
    "Unit": "t",
    "Value": 80713.79,
    "Flag": "E",
    "Flag Description": "Estimated value"
  },
  {
    "Domain Code": "QCL",
    "Domain": "Crops and livestock products",
    "Area Code": 113,
    "Area": "Kyrgyzstan",
    "Element Code": 5510,
    "Element": "Production",
    "Item Code": 27,
    "Item": "Rice",
    "Unit": "t",
    "Value": 22748.32,
    "Flag": "E",
    "Flag Description": "Estimated value"
  },
  {
    "Domain Code": "QCL",
    "Domain": "Crops and livestock products",
    "Area Code": 120,
    "Area": "Lao People's Democratic Republic",
    "Element Code": 5510,
    "Element": "Production",
    "Item Code": 27,
    "Item": "Rice",
    "Unit": "t",
    "Value": 2842878.6,
    "Flag": "E",
    "Flag Description": "Estimated value"
  },
  {
    "Domain Code": "QCL",
    "Domain": "Crops and livestock products",
    "Area Code": 119,
    "Area": "Latvia",
    "Element Code": 5510,
    "Element": "Production",
    "Item Code": 27,
    "Item": "Rice",
    "Unit": "t",
    "Value": 0,
    "Flag": "E",
    "Flag Description": "Estimated value"
  },
  {
    "Domain Code": "QCL",
    "Domain": "Crops and livestock products",
    "Area Code": 123,
    "Area": "Liberia",
    "Element Code": 5510,
    "Element": "Production",
    "Item Code": 27,
    "Item": "Rice",
    "Unit": "t",
    "Value": 211773.57,
    "Flag": "E",
    "Flag Description": "Estimated value"
  },
  {
    "Domain Code": "QCL",
    "Domain": "Crops and livestock products",
    "Area Code": 126,
    "Area": "Lithuania",
    "Element Code": 5510,
    "Element": "Production",
    "Item Code": 27,
    "Item": "Rice",
    "Unit": "t",
    "Value": 0,
    "Flag": "E",
    "Flag Description": "Estimated value"
  },
  {
    "Domain Code": "QCL",
    "Domain": "Crops and livestock products",
    "Area Code": 256,
    "Area": "Luxembourg",
    "Element Code": 5510,
    "Element": "Production",
    "Item Code": 27,
    "Item": "Rice",
    "Unit": "t",
    "Value": 0,
    "Flag": "E",
    "Flag Description": "Estimated value"
  },
  {
    "Domain Code": "QCL",
    "Domain": "Crops and livestock products",
    "Area Code": 129,
    "Area": "Madagascar",
    "Element Code": 5510,
    "Element": "Production",
    "Item Code": 27,
    "Item": "Rice",
    "Unit": "t",
    "Value": 3438054.89,
    "Flag": "E",
    "Flag Description": "Estimated value"
  },
  {
    "Domain Code": "QCL",
    "Domain": "Crops and livestock products",
    "Area Code": 130,
    "Area": "Malawi",
    "Element Code": 5510,
    "Element": "Production",
    "Item Code": 27,
    "Item": "Rice",
    "Unit": "t",
    "Value": 97653.55,
    "Flag": "E",
    "Flag Description": "Estimated value"
  },
  {
    "Domain Code": "QCL",
    "Domain": "Crops and livestock products",
    "Area Code": 131,
    "Area": "Malaysia",
    "Element Code": 5510,
    "Element": "Production",
    "Item Code": 27,
    "Item": "Rice",
    "Unit": "t",
    "Value": 2328073.32,
    "Flag": "E",
    "Flag Description": "Estimated value"
  },
  {
    "Domain Code": "QCL",
    "Domain": "Crops and livestock products",
    "Area Code": 133,
    "Area": "Mali",
    "Element Code": 5510,
    "Element": "Production",
    "Item Code": 27,
    "Item": "Rice",
    "Unit": "t",
    "Value": 1529246.81,
    "Flag": "E",
    "Flag Description": "Estimated value"
  },
  {
    "Domain Code": "QCL",
    "Domain": "Crops and livestock products",
    "Area Code": 134,
    "Area": "Malta",
    "Element Code": 5510,
    "Element": "Production",
    "Item Code": 27,
    "Item": "Rice",
    "Unit": "t",
    "Value": 0,
    "Flag": "E",
    "Flag Description": "Estimated value"
  },
  {
    "Domain Code": "QCL",
    "Domain": "Crops and livestock products",
    "Area Code": 136,
    "Area": "Mauritania",
    "Element Code": 5510,
    "Element": "Production",
    "Item Code": 27,
    "Item": "Rice",
    "Unit": "t",
    "Value": 149043.71,
    "Flag": "E",
    "Flag Description": "Estimated value"
  },
  {
    "Domain Code": "QCL",
    "Domain": "Crops and livestock products",
    "Area Code": 137,
    "Area": "Mauritius",
    "Element Code": 5510,
    "Element": "Production",
    "Item Code": 27,
    "Item": "Rice",
    "Unit": "t",
    "Value": 149.57,
    "Flag": "E",
    "Flag Description": "Estimated value"
  },
  {
    "Domain Code": "QCL",
    "Domain": "Crops and livestock products",
    "Area Code": 138,
    "Area": "Mexico",
    "Element Code": 5510,
    "Element": "Production",
    "Item Code": 27,
    "Item": "Rice",
    "Unit": "t",
    "Value": 287219.44,
    "Flag": "E",
    "Flag Description": "Estimated value"
  },
  {
    "Domain Code": "QCL",
    "Domain": "Crops and livestock products",
    "Area Code": 145,
    "Area": "Micronesia (Federated States of)",
    "Element Code": 5510,
    "Element": "Production",
    "Item Code": 27,
    "Item": "Rice",
    "Unit": "t",
    "Value": 126.49,
    "Flag": "E",
    "Flag Description": "Estimated value"
  },
  {
    "Domain Code": "QCL",
    "Domain": "Crops and livestock products",
    "Area Code": 143,
    "Area": "Morocco",
    "Element Code": 5510,
    "Element": "Production",
    "Item Code": 27,
    "Item": "Rice",
    "Unit": "t",
    "Value": 42236.3,
    "Flag": "E",
    "Flag Description": "Estimated value"
  },
  {
    "Domain Code": "QCL",
    "Domain": "Crops and livestock products",
    "Area Code": 144,
    "Area": "Mozambique",
    "Element Code": 5510,
    "Element": "Production",
    "Item Code": 27,
    "Item": "Rice",
    "Unit": "t",
    "Value": 148927.21,
    "Flag": "E",
    "Flag Description": "Estimated value"
  },
  {
    "Domain Code": "QCL",
    "Domain": "Crops and livestock products",
    "Area Code": 28,
    "Area": "Myanmar",
    "Element Code": 5510,
    "Element": "Production",
    "Item Code": 27,
    "Item": "Rice",
    "Unit": "t",
    "Value": 24753613.32,
    "Flag": "E",
    "Flag Description": "Estimated value"
  },
  {
    "Domain Code": "QCL",
    "Domain": "Crops and livestock products",
    "Area Code": 149,
    "Area": "Nepal",
    "Element Code": 5510,
    "Element": "Production",
    "Item Code": 27,
    "Item": "Rice",
    "Unit": "t",
    "Value": 4386996.31,
    "Flag": "E",
    "Flag Description": "Estimated value"
  },
  {
    "Domain Code": "QCL",
    "Domain": "Crops and livestock products",
    "Area Code": 150,
    "Area": "Netherlands (Kingdom of the)",
    "Element Code": 5510,
    "Element": "Production",
    "Item Code": 27,
    "Item": "Rice",
    "Unit": "t",
    "Value": 0,
    "Flag": "E",
    "Flag Description": "Estimated value"
  },
  {
    "Domain Code": "QCL",
    "Domain": "Crops and livestock products",
    "Area Code": 156,
    "Area": "New Zealand",
    "Element Code": 5510,
    "Element": "Production",
    "Item Code": 27,
    "Item": "Rice",
    "Unit": "t",
    "Value": 0,
    "Flag": "E",
    "Flag Description": "Estimated value"
  },
  {
    "Domain Code": "QCL",
    "Domain": "Crops and livestock products",
    "Area Code": 157,
    "Area": "Nicaragua",
    "Element Code": 5510,
    "Element": "Production",
    "Item Code": 27,
    "Item": "Rice",
    "Unit": "t",
    "Value": 336544.79,
    "Flag": "E",
    "Flag Description": "Estimated value"
  },
  {
    "Domain Code": "QCL",
    "Domain": "Crops and livestock products",
    "Area Code": 158,
    "Area": "Niger",
    "Element Code": 5510,
    "Element": "Production",
    "Item Code": 27,
    "Item": "Rice",
    "Unit": "t",
    "Value": 78557.76,
    "Flag": "E",
    "Flag Description": "Estimated value"
  },
  {
    "Domain Code": "QCL",
    "Domain": "Crops and livestock products",
    "Area Code": 159,
    "Area": "Nigeria",
    "Element Code": 5510,
    "Element": "Production",
    "Item Code": 27,
    "Item": "Rice",
    "Unit": "t",
    "Value": 5092752.18,
    "Flag": "E",
    "Flag Description": "Estimated value"
  },
  {
    "Domain Code": "QCL",
    "Domain": "Crops and livestock products",
    "Area Code": 154,
    "Area": "North Macedonia",
    "Element Code": 5510,
    "Element": "Production",
    "Item Code": 27,
    "Item": "Rice",
    "Unit": "t",
    "Value": 18937.75,
    "Flag": "E",
    "Flag Description": "Estimated value"
  },
  {
    "Domain Code": "QCL",
    "Domain": "Crops and livestock products",
    "Area Code": 165,
    "Area": "Pakistan",
    "Element Code": 5510,
    "Element": "Production",
    "Item Code": 27,
    "Item": "Rice",
    "Unit": "t",
    "Value": 8617398.66,
    "Flag": "E",
    "Flag Description": "Estimated value"
  },
  {
    "Domain Code": "QCL",
    "Domain": "Crops and livestock products",
    "Area Code": 166,
    "Area": "Panama",
    "Element Code": 5510,
    "Element": "Production",
    "Item Code": 27,
    "Item": "Rice",
    "Unit": "t",
    "Value": 292920.11,
    "Flag": "E",
    "Flag Description": "Estimated value"
  },
  {
    "Domain Code": "QCL",
    "Domain": "Crops and livestock products",
    "Area Code": 168,
    "Area": "Papua New Guinea",
    "Element Code": 5510,
    "Element": "Production",
    "Item Code": 27,
    "Item": "Rice",
    "Unit": "t",
    "Value": 782.78,
    "Flag": "E",
    "Flag Description": "Estimated value"
  },
  {
    "Domain Code": "QCL",
    "Domain": "Crops and livestock products",
    "Area Code": 169,
    "Area": "Paraguay",
    "Element Code": 5510,
    "Element": "Production",
    "Item Code": 27,
    "Item": "Rice",
    "Unit": "t",
    "Value": 403464.07,
    "Flag": "E",
    "Flag Description": "Estimated value"
  },
  {
    "Domain Code": "QCL",
    "Domain": "Crops and livestock products",
    "Area Code": 170,
    "Area": "Peru",
    "Element Code": 5510,
    "Element": "Production",
    "Item Code": 27,
    "Item": "Rice",
    "Unit": "t",
    "Value": 2469299.23,
    "Flag": "E",
    "Flag Description": "Estimated value"
  },
  {
    "Domain Code": "QCL",
    "Domain": "Crops and livestock products",
    "Area Code": 171,
    "Area": "Philippines",
    "Element Code": 5510,
    "Element": "Production",
    "Item Code": 27,
    "Item": "Rice",
    "Unit": "t",
    "Value": 15354345.88,
    "Flag": "E",
    "Flag Description": "Estimated value"
  },
  {
    "Domain Code": "QCL",
    "Domain": "Crops and livestock products",
    "Area Code": 173,
    "Area": "Poland",
    "Element Code": 5510,
    "Element": "Production",
    "Item Code": 27,
    "Item": "Rice",
    "Unit": "t",
    "Value": 0,
    "Flag": "E",
    "Flag Description": "Estimated value"
  },
  {
    "Domain Code": "QCL",
    "Domain": "Crops and livestock products",
    "Area Code": 174,
    "Area": "Portugal",
    "Element Code": 5510,
    "Element": "Production",
    "Item Code": 27,
    "Item": "Rice",
    "Unit": "t",
    "Value": 158648.29,
    "Flag": "E",
    "Flag Description": "Estimated value"
  },
  {
    "Domain Code": "QCL",
    "Domain": "Crops and livestock products",
    "Area Code": 177,
    "Area": "Puerto Rico",
    "Element Code": 5510,
    "Element": "Production",
    "Item Code": 27,
    "Item": "Rice",
    "Unit": "t",
    "Value": 45.48,
    "Flag": "E",
    "Flag Description": "Estimated value"
  },
  {
    "Domain Code": "QCL",
    "Domain": "Crops and livestock products",
    "Area Code": 117,
    "Area": "Republic of Korea",
    "Element Code": 5510,
    "Element": "Production",
    "Item Code": 27,
    "Item": "Rice",
    "Unit": "t",
    "Value": 6152779.14,
    "Flag": "E",
    "Flag Description": "Estimated value"
  },
  {
    "Domain Code": "QCL",
    "Domain": "Crops and livestock products",
    "Area Code": 146,
    "Area": "Republic of Moldova",
    "Element Code": 5510,
    "Element": "Production",
    "Item Code": 27,
    "Item": "Rice",
    "Unit": "t",
    "Value": 0,
    "Flag": "E",
    "Flag Description": "Estimated value"
  },
  {
    "Domain Code": "QCL",
    "Domain": "Crops and livestock products",
    "Area Code": 182,
    "Area": "Réunion",
    "Element Code": 5510,
    "Element": "Production",
    "Item Code": 27,
    "Item": "Rice",
    "Unit": "t",
    "Value": 123.85,
    "Flag": "E",
    "Flag Description": "Estimated value"
  },
  {
    "Domain Code": "QCL",
    "Domain": "Crops and livestock products",
    "Area Code": 183,
    "Area": "Romania",
    "Element Code": 5510,
    "Element": "Production",
    "Item Code": 27,
    "Item": "Rice",
    "Unit": "t",
    "Value": 28951.46,
    "Flag": "E",
    "Flag Description": "Estimated value"
  },
  {
    "Domain Code": "QCL",
    "Domain": "Crops and livestock products",
    "Area Code": 185,
    "Area": "Russian Federation",
    "Element Code": 5510,
    "Element": "Production",
    "Item Code": 27,
    "Item": "Rice",
    "Unit": "t",
    "Value": 761961.08,
    "Flag": "E",
    "Flag Description": "Estimated value"
  },
  {
    "Domain Code": "QCL",
    "Domain": "Crops and livestock products",
    "Area Code": 184,
    "Area": "Rwanda",
    "Element Code": 5510,
    "Element": "Production",
    "Item Code": 27,
    "Item": "Rice",
    "Unit": "t",
    "Value": 61485.12,
    "Flag": "E",
    "Flag Description": "Estimated value"
  },
  {
    "Domain Code": "QCL",
    "Domain": "Crops and livestock products",
    "Area Code": 191,
    "Area": "Saint Vincent and the Grenadines",
    "Element Code": 5510,
    "Element": "Production",
    "Item Code": 27,
    "Item": "Rice",
    "Unit": "t",
    "Value": 0,
    "Flag": "E",
    "Flag Description": "Estimated value"
  },
  {
    "Domain Code": "QCL",
    "Domain": "Crops and livestock products",
    "Area Code": 194,
    "Area": "Saudi Arabia",
    "Element Code": 5510,
    "Element": "Production",
    "Item Code": 27,
    "Item": "Rice",
    "Unit": "t",
    "Value": 72.54,
    "Flag": "E",
    "Flag Description": "Estimated value"
  },
  {
    "Domain Code": "QCL",
    "Domain": "Crops and livestock products",
    "Area Code": 195,
    "Area": "Senegal",
    "Element Code": 5510,
    "Element": "Production",
    "Item Code": 27,
    "Item": "Rice",
    "Unit": "t",
    "Value": 505468.89,
    "Flag": "E",
    "Flag Description": "Estimated value"
  },
  {
    "Domain Code": "QCL",
    "Domain": "Crops and livestock products",
    "Area Code": 197,
    "Area": "Sierra Leone",
    "Element Code": 5510,
    "Element": "Production",
    "Item Code": 27,
    "Item": "Rice",
    "Unit": "t",
    "Value": 760745.79,
    "Flag": "E",
    "Flag Description": "Estimated value"
  },
  {
    "Domain Code": "QCL",
    "Domain": "Crops and livestock products",
    "Area Code": 199,
    "Area": "Slovakia",
    "Element Code": 5510,
    "Element": "Production",
    "Item Code": 27,
    "Item": "Rice",
    "Unit": "t",
    "Value": 0,
    "Flag": "E",
    "Flag Description": "Estimated value"
  },
  {
    "Domain Code": "QCL",
    "Domain": "Crops and livestock products",
    "Area Code": 198,
    "Area": "Slovenia",
    "Element Code": 5510,
    "Element": "Production",
    "Item Code": 27,
    "Item": "Rice",
    "Unit": "t",
    "Value": 0,
    "Flag": "E",
    "Flag Description": "Estimated value"
  },
  {
    "Domain Code": "QCL",
    "Domain": "Crops and livestock products",
    "Area Code": 25,
    "Area": "Solomon Islands",
    "Element Code": 5510,
    "Element": "Production",
    "Item Code": 27,
    "Item": "Rice",
    "Unit": "t",
    "Value": 2671.24,
    "Flag": "E",
    "Flag Description": "Estimated value"
  },
  {
    "Domain Code": "QCL",
    "Domain": "Crops and livestock products",
    "Area Code": 201,
    "Area": "Somalia",
    "Element Code": 5510,
    "Element": "Production",
    "Item Code": 27,
    "Item": "Rice",
    "Unit": "t",
    "Value": 5500.47,
    "Flag": "E",
    "Flag Description": "Estimated value"
  },
  {
    "Domain Code": "QCL",
    "Domain": "Crops and livestock products",
    "Area Code": 202,
    "Area": "South Africa",
    "Element Code": 5510,
    "Element": "Production",
    "Item Code": 27,
    "Item": "Rice",
    "Unit": "t",
    "Value": 3071.9,
    "Flag": "E",
    "Flag Description": "Estimated value"
  },
  {
    "Domain Code": "QCL",
    "Domain": "Crops and livestock products",
    "Area Code": 277,
    "Area": "South Sudan",
    "Element Code": 5510,
    "Element": "Production",
    "Item Code": 27,
    "Item": "Rice",
    "Unit": "t",
    "Value": 13242.2,
    "Flag": "E",
    "Flag Description": "Estimated value"
  },
  {
    "Domain Code": "QCL",
    "Domain": "Crops and livestock products",
    "Area Code": 203,
    "Area": "Spain",
    "Element Code": 5510,
    "Element": "Production",
    "Item Code": 27,
    "Item": "Rice",
    "Unit": "t",
    "Value": 783551.18,
    "Flag": "E",
    "Flag Description": "Estimated value"
  },
  {
    "Domain Code": "QCL",
    "Domain": "Crops and livestock products",
    "Area Code": 38,
    "Area": "Sri Lanka",
    "Element Code": 5510,
    "Element": "Production",
    "Item Code": 27,
    "Item": "Rice",
    "Unit": "t",
    "Value": 3470047.71,
    "Flag": "E",
    "Flag Description": "Estimated value"
  },
  {
    "Domain Code": "QCL",
    "Domain": "Crops and livestock products",
    "Area Code": 276,
    "Area": "Sudan",
    "Element Code": 5510,
    "Element": "Production",
    "Item Code": 27,
    "Item": "Rice",
    "Unit": "t",
    "Value": 27903.33,
    "Flag": "E",
    "Flag Description": "Estimated value"
  },
  {
    "Domain Code": "QCL",
    "Domain": "Crops and livestock products",
    "Area Code": 206,
    "Area": "Sudan (former)",
    "Element Code": 5510,
    "Element": "Production",
    "Item Code": 27,
    "Item": "Rice",
    "Unit": "t",
    "Value": 14913.78,
    "Flag": "E",
    "Flag Description": "Estimated value"
  },
  {
    "Domain Code": "QCL",
    "Domain": "Crops and livestock products",
    "Area Code": 207,
    "Area": "Suriname",
    "Element Code": 5510,
    "Element": "Production",
    "Item Code": 27,
    "Item": "Rice",
    "Unit": "t",
    "Value": 220865.57,
    "Flag": "E",
    "Flag Description": "Estimated value"
  },
  {
    "Domain Code": "QCL",
    "Domain": "Crops and livestock products",
    "Area Code": 210,
    "Area": "Sweden",
    "Element Code": 5510,
    "Element": "Production",
    "Item Code": 27,
    "Item": "Rice",
    "Unit": "t",
    "Value": 0,
    "Flag": "E",
    "Flag Description": "Estimated value"
  },
  {
    "Domain Code": "QCL",
    "Domain": "Crops and livestock products",
    "Area Code": 212,
    "Area": "Syrian Arab Republic",
    "Element Code": 5510,
    "Element": "Production",
    "Item Code": 27,
    "Item": "Rice",
    "Unit": "t",
    "Value": 16,
    "Flag": "E",
    "Flag Description": "Estimated value"
  },
  {
    "Domain Code": "QCL",
    "Domain": "Crops and livestock products",
    "Area Code": 208,
    "Area": "Tajikistan",
    "Element Code": 5510,
    "Element": "Production",
    "Item Code": 27,
    "Item": "Rice",
    "Unit": "t",
    "Value": 64084.97,
    "Flag": "E",
    "Flag Description": "Estimated value"
  },
  {
    "Domain Code": "QCL",
    "Domain": "Crops and livestock products",
    "Area Code": 216,
    "Area": "Thailand",
    "Element Code": 5510,
    "Element": "Production",
    "Item Code": 27,
    "Item": "Rice",
    "Unit": "t",
    "Value": 29793897.07,
    "Flag": "E",
    "Flag Description": "Estimated value"
  },
  {
    "Domain Code": "QCL",
    "Domain": "Crops and livestock products",
    "Area Code": 176,
    "Area": "Timor-Leste",
    "Element Code": 5510,
    "Element": "Production",
    "Item Code": 27,
    "Item": "Rice",
    "Unit": "t",
    "Value": 63725.07,
    "Flag": "E",
    "Flag Description": "Estimated value"
  },
  {
    "Domain Code": "QCL",
    "Domain": "Crops and livestock products",
    "Area Code": 217,
    "Area": "Togo",
    "Element Code": 5510,
    "Element": "Production",
    "Item Code": 27,
    "Item": "Rice",
    "Unit": "t",
    "Value": 107124.39,
    "Flag": "E",
    "Flag Description": "Estimated value"
  },
  {
    "Domain Code": "QCL",
    "Domain": "Crops and livestock products",
    "Area Code": 220,
    "Area": "Trinidad and Tobago",
    "Element Code": 5510,
    "Element": "Production",
    "Item Code": 27,
    "Item": "Rice",
    "Unit": "t",
    "Value": 3953.72,
    "Flag": "E",
    "Flag Description": "Estimated value"
  },
  {
    "Domain Code": "QCL",
    "Domain": "Crops and livestock products",
    "Area Code": 223,
    "Area": "Türkiye",
    "Element Code": 5510,
    "Element": "Production",
    "Item Code": 27,
    "Item": "Rice",
    "Unit": "t",
    "Value": 645333.04,
    "Flag": "E",
    "Flag Description": "Estimated value"
  },
  {
    "Domain Code": "QCL",
    "Domain": "Crops and livestock products",
    "Area Code": 213,
    "Area": "Turkmenistan",
    "Element Code": 5510,
    "Element": "Production",
    "Item Code": 27,
    "Item": "Rice",
    "Unit": "t",
    "Value": 79059.35,
    "Flag": "E",
    "Flag Description": "Estimated value"
  },
  {
    "Domain Code": "QCL",
    "Domain": "Crops and livestock products",
    "Area Code": 226,
    "Area": "Uganda",
    "Element Code": 5510,
    "Element": "Production",
    "Item Code": 27,
    "Item": "Rice",
    "Unit": "t",
    "Value": 169538.11,
    "Flag": "E",
    "Flag Description": "Estimated value"
  },
  {
    "Domain Code": "QCL",
    "Domain": "Crops and livestock products",
    "Area Code": 230,
    "Area": "Ukraine",
    "Element Code": 5510,
    "Element": "Production",
    "Item Code": 27,
    "Item": "Rice",
    "Unit": "t",
    "Value": 88377.36,
    "Flag": "E",
    "Flag Description": "Estimated value"
  },
  {
    "Domain Code": "QCL",
    "Domain": "Crops and livestock products",
    "Area Code": 215,
    "Area": "United Republic of Tanzania",
    "Element Code": 5510,
    "Element": "Production",
    "Item Code": 27,
    "Item": "Rice",
    "Unit": "t",
    "Value": 1615693.61,
    "Flag": "E",
    "Flag Description": "Estimated value"
  },
  {
    "Domain Code": "QCL",
    "Domain": "Crops and livestock products",
    "Area Code": 231,
    "Area": "United States of America",
    "Element Code": 5510,
    "Element": "Production",
    "Item Code": 27,
    "Item": "Rice",
    "Unit": "t",
    "Value": 9182939.29,
    "Flag": "E",
    "Flag Description": "Estimated value"
  },
  {
    "Domain Code": "QCL",
    "Domain": "Crops and livestock products",
    "Area Code": 234,
    "Area": "Uruguay",
    "Element Code": 5510,
    "Element": "Production",
    "Item Code": 27,
    "Item": "Rice",
    "Unit": "t",
    "Value": 1188260.64,
    "Flag": "E",
    "Flag Description": "Estimated value"
  },
  {
    "Domain Code": "QCL",
    "Domain": "Crops and livestock products",
    "Area Code": 235,
    "Area": "Uzbekistan",
    "Element Code": 5510,
    "Element": "Production",
    "Item Code": 27,
    "Item": "Rice",
    "Unit": "t",
    "Value": 291545.18,
    "Flag": "E",
    "Flag Description": "Estimated value"
  },
  {
    "Domain Code": "QCL",
    "Domain": "Crops and livestock products",
    "Area Code": 236,
    "Area": "Venezuela (Bolivarian Republic of)",
    "Element Code": 5510,
    "Element": "Production",
    "Item Code": 27,
    "Item": "Rice",
    "Unit": "t",
    "Value": 828845.21,
    "Flag": "E",
    "Flag Description": "Estimated value"
  },
  {
    "Domain Code": "QCL",
    "Domain": "Crops and livestock products",
    "Area Code": 237,
    "Area": "Viet Nam",
    "Element Code": 5510,
    "Element": "Production",
    "Item Code": 27,
    "Item": "Rice",
    "Unit": "t",
    "Value": 37092964.67,
    "Flag": "E",
    "Flag Description": "Estimated value"
  },
  {
    "Domain Code": "QCL",
    "Domain": "Crops and livestock products",
    "Area Code": 251,
    "Area": "Zambia",
    "Element Code": 5510,
    "Element": "Production",
    "Item Code": 27,
    "Item": "Rice",
    "Unit": "t",
    "Value": 26664.3,
    "Flag": "E",
    "Flag Description": "Estimated value"
  },
  {
    "Domain Code": "QCL",
    "Domain": "Crops and livestock products",
    "Area Code": 181,
    "Area": "Zimbabwe",
    "Element Code": 5510,
    "Element": "Production",
    "Item Code": 27,
    "Item": "Rice",
    "Unit": "t",
    "Value": 906.64,
    "Flag": "E",
    "Flag Description": "Estimated value"
  }
]
